setup.py
text_classifikation/__init__.py
text_classifikation/settings.py
text_classifikation.egg-info/PKG-INFO
text_classifikation.egg-info/SOURCES.txt
text_classifikation.egg-info/dependency_links.txt
text_classifikation.egg-info/top_level.txt
text_classifikation/classifiers/__init__.py
text_classifikation/classifiers/pipelines.py
text_classifikation/classifiers/adaboost/__init__.py
text_classifikation/classifiers/forest/__init__.py
text_classifikation/classifiers/gradboost/__init__.py
text_classifikation/classifiers/logreg/__init__.py
text_classifikation/classifiers/naive/__init__.py
text_classifikation/classifiers/passive_agressive/__init__.py
text_classifikation/classifiers/perceptron/__init__.py
text_classifikation/classifiers/ridge/__init__.py
text_classifikation/classifiers/sgd/__init__.py
text_classifikation/classifiers/svm/__init__.py
text_classifikation/classifiers/tree/__init__.py
text_classifikation/features/__init__.py
text_classifikation/features/doc2vec.py
text_classifikation/features/gensim_transformers.py
text_classifikation/features/preprocess.py
text_classifikation/features/word_vecs.py