Metadata-Version: 1.0
Name: text-classifikation
Version: 0.1
Summary: utils to find best text classifier for your data
Home-page: https://github.com/JarbasAl/text_classifikation
Author: jarbasAI
Author-email: jarbasai@mailfence.com
License: MIT
Platform: UNKNOWN
